colormap/__init__.py
colormap/colors.py
colormap/get_cmap.py
colormap/xfree86.py
colormap-1.3.0.dist-info/LICENSE
colormap-1.3.0.dist-info/METADATA
colormap-1.3.0.dist-info/WHEEL
colormap-1.3.0.dist-info/RECORD
