Metadata-Version: 2.3
Name: colormap
Version: 1.3.0
Summary: Commn utilities to ease development of Python packages
License: BSD-3-Clause
Keywords: config,decorators,development
Author: Thomas Cokelaer
Author-email: thomas.cokelaer@pasteur.fr
Requires-Python: >=3.8,<4.0
Classifier: Development Status :: 5 - Production/Stable
Classifier: Intended Audience :: Education
Classifier: Intended Audience :: End Users/Desktop
Classifier: Intended Audience :: Developers
Classifier: Intended Audience :: Science/Research
Classifier: License :: OSI Approved :: BSD License
Classifier: Operating System :: POSIX :: Linux
Classifier: Programming Language :: Python :: 3.9
Classifier: Programming Language :: Python :: 3.10
Classifier: Programming Language :: Python :: 3.11
Classifier: Programming Language :: Python :: 3.12
Classifier: Topic :: Software Development :: Libraries :: Python Modules
Classifier: Topic :: Scientific/Engineering :: Bio-Informatics
Classifier: Topic :: Scientific/Engineering :: Information Analysis
Requires-Dist: importlib_resources (>6) ; python_version >= "3.9" and python_full_version <= "3.10.0"
Requires-Dist: matplotlib (>=3,<4) ; python_version < "3.12"
Requires-Dist: matplotlib (>=3.9.2,<4.0.0) ; python_version >= "3.12" and python_version < "4.0"
Requires-Dist: numpy (<2) ; python_version < "3.10"
Requires-Dist: numpy (>=2,<3) ; python_version >= "3.10" and python_version < "4.0"
Project-URL: Documentation, https://colormap.readthedocs.io
Project-URL: Homepage, https://colormap/dev.readthedocs.io
Project-URL: Issues, https://github.com/cokelaer/colormap/issues
Project-URL: Repository, https://github.com/cokelaer/colormap
